samcli/__init__.py
samcli/__main__.py
samcli/yamlhelper.py
samcli/cli/__init__.py
samcli/cli/cli_config_file.py
samcli/cli/command.py
samcli/cli/context.py
samcli/cli/global_config.py
samcli/cli/main.py
samcli/cli/options.py
samcli/cli/types.py
samcli/commands/__init__.py
samcli/commands/exceptions.py
samcli/commands/_utils/__init__.py
samcli/commands/_utils/options.py
samcli/commands/_utils/resources.py
samcli/commands/_utils/table_print.py
samcli/commands/_utils/template.py
samcli/commands/_utils/custom_options/__init__.py
samcli/commands/_utils/custom_options/option_nargs.py
samcli/commands/bootstrap/__init__.py
samcli/commands/bootstrap/command.py
samcli/commands/bootstrap/exceptions.py
samcli/commands/build/__init__.py
samcli/commands/build/build_context.py
samcli/commands/build/command.py
samcli/commands/build/exceptions.py
samcli/commands/deploy/__init__.py
samcli/commands/deploy/command.py
samcli/commands/deploy/deploy_context.py
samcli/commands/deploy/exceptions.py
samcli/commands/deploy/guided_config.py
samcli/commands/deploy/guided_context.py
samcli/commands/deploy/utils.py
samcli/commands/init/__init__.py
samcli/commands/init/init_generator.py
samcli/commands/init/init_templates.py
samcli/commands/init/interactive_event_bridge_flow.py
samcli/commands/init/interactive_init_flow.py
samcli/commands/local/__init__.py
samcli/commands/local/local.py
samcli/commands/local/cli_common/__init__.py
samcli/commands/local/cli_common/invoke_context.py
samcli/commands/local/cli_common/options.py
samcli/commands/local/cli_common/user_exceptions.py
samcli/commands/local/generate_event/__init__.py
samcli/commands/local/generate_event/cli.py
samcli/commands/local/generate_event/event_generation.py
samcli/commands/local/invoke/__init__.py
samcli/commands/local/invoke/cli.py
samcli/commands/local/lib/__init__.py
samcli/commands/local/lib/debug_context.py
samcli/commands/local/lib/exceptions.py
samcli/commands/local/lib/local_api_service.py
aws_sam_cli_without_docker-0.45.0.dist-info/LICENSE
aws_sam_cli_without_docker-0.45.0.dist-info/METADATA
aws_sam_cli_without_docker-0.45.0.dist-info/NOTICE
aws_sam_cli_without_docker-0.45.0.dist-info/WHEEL
aws_sam_cli_without_docker-0.45.0.dist-info/entry_points.txt
aws_sam_cli_without_docker-0.45.0.dist-info/top_level.txt
aws_sam_cli_without_docker-0.45.0.dist-info/RECORD
