Metadata-Version: 2.1
Name: aws-sam-cli-without-docker
Version: 0.45.0
Summary: AWS SAM CLI is a CLI tool for local development and testing of Serverless applications
Home-page: https://github.com/theowenyoung/aws-sam-cli
Author: Amazon Web Services
Author-email: aws-sam-developers@amazon.com
License: Apache License 2.0
Keywords: AWS SAM CLI
Platform: UNKNOWN
Classifier: Development Status :: 4 - Beta
Classifier: Environment :: Console
Classifier: Environment :: Other Environment
Classifier: Intended Audience :: Developers
Classifier: Intended Audience :: Information Technology
Classifier: License :: OSI Approved :: Apache Software License
Classifier: Operating System :: OS Independent
Classifier: Programming Language :: Python
Classifier: Programming Language :: Python :: 3.6
Classifier: Programming Language :: Python :: 3.7
Classifier: Programming Language :: Python :: 3.8
Classifier: Topic :: Internet
Classifier: Topic :: Software Development :: Build Tools
Classifier: Topic :: Utilities
Requires-Python: >=3.6, <=4.0, !=4.0
Requires-Dist: chevron (~=0.12)
Requires-Dist: click (~=7.0)
Requires-Dist: Flask (~=1.0.2)
Requires-Dist: boto3 (>=1.10.29,~=1.10)
Requires-Dist: jmespath (~=0.9.5)
Requires-Dist: PyYAML (~=5.1)
Requires-Dist: cookiecutter (~=1.6.0)
Requires-Dist: aws-sam-translator (==1.22.0)
Requires-Dist: docker (~=4.0)
Requires-Dist: dateparser (~=0.7)
Requires-Dist: python-dateutil (<2.8.1,~=2.6)
Requires-Dist: requests (==2.22.0)
Requires-Dist: serverlessrepo (==0.1.9)
Requires-Dist: aws-lambda-builders (==0.8.0)
Requires-Dist: tomlkit (==0.5.8)
Provides-Extra: dev
Requires-Dist: coverage (==4.5.4) ; extra == 'dev'
Requires-Dist: pytest-cov (==2.7.1) ; extra == 'dev'
Requires-Dist: pylint (==2.3.1) ; extra == 'dev'
Requires-Dist: pytest (==5.2.1) ; extra == 'dev'
Requires-Dist: parameterized (==0.7.0) ; extra == 'dev'
Requires-Dist: pytest-xdist (==1.30.0) ; extra == 'dev'
Requires-Dist: pytest-forked (==1.1.3) ; extra == 'dev'
Requires-Dist: pytest-timeout (==1.3.3) ; extra == 'dev'
Requires-Dist: pytest-rerunfailures (==7.0) ; extra == 'dev'
